karrio/mappers/spring/__init__.py
karrio/mappers/spring/mapper.py
karrio/mappers/spring/proxy.py
karrio/mappers/spring/settings.py
karrio/plugins/spring/__init__.py
karrio/providers/spring/__init__.py
karrio/providers/spring/error.py
karrio/providers/spring/tracking.py
karrio/providers/spring/units.py
karrio/providers/spring/utils.py
karrio/providers/spring/shipment/__init__.py
karrio/providers/spring/shipment/cancel.py
karrio/providers/spring/shipment/create.py
karrio/schemas/spring/__init__.py
karrio/schemas/spring/error_response.py
karrio/schemas/spring/shipment_cancel_request.py
karrio/schemas/spring/shipment_cancel_response.py
karrio/schemas/spring/shipment_request.py
karrio/schemas/spring/shipment_response.py
karrio/schemas/spring/tracking_request.py
karrio/schemas/spring/tracking_response.py
karrio_spring-2026.1.4.dist-info/METADATA
karrio_spring-2026.1.4.dist-info/WHEEL
karrio_spring-2026.1.4.dist-info/entry_points.txt
karrio_spring-2026.1.4.dist-info/top_level.txt
karrio_spring-2026.1.4.dist-info/RECORD
